tempground/__init__.py
tempground/_dir_from_template.py
tempground/_errors.py
tempground/_files.py
tempground/_temp_project.py
tempground/py.typed
tempground-0.4.3.dist-info/LICENSE
tempground-0.4.3.dist-info/METADATA
tempground-0.4.3.dist-info/WHEEL
tempground-0.4.3.dist-info/top_level.txt
tempground-0.4.3.dist-info/RECORD
