Metadata-Version: 2.1
Name: tempground
Version: 0.4.3
Author: Artsiom iG
Author-email: ortemeo@gmail.com
License: MIT
Keywords: temp,temporary,project,sandbox,library,unit,testing,integration
Classifier: Programming Language :: Python :: 3.10
Classifier: Programming Language :: Python :: 3.11
Classifier: Typing :: Typed
Classifier: Operating System :: POSIX :: Linux
Classifier: Operating System :: MacOS
Classifier: Operating System :: Microsoft :: Windows
Requires-Python: >=3.10, <4
License-File: LICENSE
